livekit/plugins/noise_cancellation/__init__.py
livekit/plugins/noise_cancellation/plugin.py
livekit/plugins/noise_cancellation/py.typed
livekit/plugins/noise_cancellation/resources/c8.f.s.026300-1.0.0_3.1.kef
livekit/plugins/noise_cancellation/resources/hs.c6.f.m.75df8f.kef
livekit/plugins/noise_cancellation/resources/inb.bvc.hs.c6.w.s.23cdb3.kef
livekit/plugins/noise_cancellation/resources/liblivekit_nc_plugin.dylib
livekit_plugins_noise_cancellation-0.2.5.dist-info/METADATA
livekit_plugins_noise_cancellation-0.2.5.dist-info/WHEEL
livekit_plugins_noise_cancellation-0.2.5.dist-info/top_level.txt
livekit_plugins_noise_cancellation-0.2.5.dist-info/RECORD
