Metadata-Version: 2.4
Name: livekit-plugins-noise-cancellation
Version: 0.2.5
Summary: Livekit plugin for noise cancellation of inbound AudioStream
License: SEE LICENSE IN https://livekit.io/legal/terms-of-service
Keywords: webrtc,realtime,audio,livekit
Requires-Python: >=3.9
Requires-Dist: livekit>=0.21.3
